easypg/__init__.py
easypg/exceptions.py
easypg/main.py
easy_pgsql-0.0.1.dist-info/METADATA
easy_pgsql-0.0.1.dist-info/WHEEL
easy_pgsql-0.0.1.dist-info/top_level.txt
easy_pgsql-0.0.1.dist-info/RECORD
